manuelharofulgencio4/__init__.py
manuelharofulgencio4/opengate_client.py
manuelharofulgencio4/ai_models/__init__.py
manuelharofulgencio4/ai_models/ai_models.py
manuelharofulgencio4/ai_pipelines/__init__.py
manuelharofulgencio4/ai_pipelines/ai_pipelines.py
manuelharofulgencio4/ai_transformers/__init__.py
manuelharofulgencio4/ai_transformers/ai_transformers.py
manuelharofulgencio4/datapoints/__init__.py
manuelharofulgencio4/datapoints/datapoints.py
manuelharofulgencio4/datasets/__init__.py
manuelharofulgencio4/datasets/datasets.py
manuelharofulgencio4/entities/__init__.py
manuelharofulgencio4/entities/entities.py
manuelharofulgencio4/rules/__init__.py
manuelharofulgencio4/rules/rules.py
manuelharofulgencio4/test/__init__.py
manuelharofulgencio4/test/ownworld.py
manuelharofulgencio4/test/test_steps_cucumber.py
manuelharofulgencio4/timeseries/__init__.py
manuelharofulgencio4/timeseries/timeseries.py
manuelharofulgencio4-1.0.0.dist-info/METADATA
manuelharofulgencio4-1.0.0.dist-info/WHEEL
manuelharofulgencio4-1.0.0.dist-info/top_level.txt
manuelharofulgencio4-1.0.0.dist-info/RECORD
